django_richenum/__init__.py
django_richenum/admin/__init__.py
django_richenum/admin/filters.py
django_richenum/admin/options.py
django_richenum/forms/__init__.py
django_richenum/forms/fields.py
django_richenum/models/__init__.py
django_richenum/models/fields.py
django_richenum-5.0.0.dist-info/AUTHORS.rst
django_richenum-5.0.0.dist-info/LICENSE.txt
django_richenum-5.0.0.dist-info/METADATA
django_richenum-5.0.0.dist-info/WHEEL
django_richenum-5.0.0.dist-info/top_level.txt
django_richenum-5.0.0.dist-info/RECORD
