Metadata-Version: 2.1
Name: django-richenum
Version: 5.0.0
Summary: Django Enum library for python.
Home-page: https://github.com/hearsaycorp/django-richenum
Author: Hearsay Social
Author-email: opensource@hearsaysocial.com
License: MIT
Keywords: python django enum richenum
Classifier: Development Status :: 5 - Production/Stable
Classifier: License :: OSI Approved :: MIT License
Classifier: Programming Language :: Python :: 3.8
Classifier: Programming Language :: Python :: 3.9
Classifier: Programming Language :: Python :: 3.10
Classifier: Programming Language :: Python :: 3.11
Classifier: Programming Language :: Python :: Implementation :: CPython
License-File: LICENSE.txt
License-File: AUTHORS.rst
Requires-Dist: Django <4.3,>=3.2
Requires-Dist: richenum
